easyui-0.2.1.dist-info/DESCRIPTION.rst
easyui-0.2.1.dist-info/RECORD
easyui-0.2.1.dist-info/METADATA
easyui-0.2.1.dist-info/WHEEL
easyui-0.2.1.dist-info/top_level.txt
easyui-0.2.1.dist-info/metadata.json
easyui/__init__.py
easyui/admin.py
easyui/utils.py
easyui/urls.py
easyui/models.py
easyui/tests.py
easyui/views.py
easyui/forms.py
easyui/initial_data.json
easyui/migrations/__init__.py
easyui/migrations/0002_auto_20141223_1924.py
easyui/migrations/0004_groupmenu.py
easyui/migrations/__init__.pyc
easyui/migrations/0003_auto_20141225_1204.py
easyui/migrations/0001_initial.py
easyui/templates/500.html
easyui/templates/base.html
easyui/templates/404.html
easyui/templates/login.html
easyui/templates/tpl/README.txt
easyui/templates/tpl/dialog_command.html
easyui/templates/tpl/date_start_end.html
easyui/templates/tpl/command_process.html
easyui/templates/tpl/dialog.html
easyui/templates/tpl/datetime_start_end.html
easyui/templates/tpl/status.html
easyui/templates/tpl/home/head_js.html
easyui/templates/tpl/home/custom_js.html
easyui/templates/tpl/home/left_menu.html
easyui/templates/tpl/home/custom_css.html
easyui/templates/tpl/home/theme.html
easyui/templates/base/README.txt
easyui/templates/base/single_panel.html
easyui/templates/base/home.html
easyui/templates/easyui/command_datagrid.html
easyui/templates/easyui/usermenu_form.html
easyui/templates/easyui/menu_confirm_delete.html
easyui/templates/easyui/groupmenu_form.html
easyui/templates/easyui/datagrid.html
easyui/templates/easyui/menu_right_menu.html
easyui/templates/easyui/menu_list.html
easyui/templates/easyui/form.html
easyui/templates/easyui/menu_form.html
easyui/templates/easyui/confirm_delete.html
easyui/mixins/__init__.py
easyui/mixins/view_mixins.py
easyui/mixins/permission_mixins.py
easyui/mixins/easyui_mixins.py
easyui/mixins/model_mixins.py
easyui/static/fonts/glyphicons-halflings-regular.ttf
easyui/static/fonts/glyphicons-halflings-regular.eot
easyui/static/fonts/glyphicons-halflings-regular.svg
easyui/static/fonts/glyphicons-halflings-regular.woff
easyui/static/css/bootstrap.min.css
easyui/static/css/om.css
easyui/static/css/custom/general.css
